LICENSE
MANIFEST.in
README.rst
setup.py
tastypie_msgpack/__init__.py
tastypie_msgpack.egg-info/PKG-INFO
tastypie_msgpack.egg-info/SOURCES.txt
tastypie_msgpack.egg-info/dependency_links.txt
tastypie_msgpack.egg-info/requires.txt
tastypie_msgpack.egg-info/top_level.txt